LICENSE.md
MANIFEST.in
README.md
pyproject.toml
game_bot_helper.egg-info/PKG-INFO
game_bot_helper.egg-info/SOURCES.txt
game_bot_helper.egg-info/dependency_links.txt
game_bot_helper.egg-info/requires.txt
game_bot_helper.egg-info/top_level.txt
src/game-bot-helper/GameBotHelper.py
src/game-bot-helper/ThreadWithTrace.py
src/game-bot-helper/__init__.py
src/game-bot-helper/config.toml
src/game-bot-helper/debug.py
venv/Lib/site-packages/__editable___game_bot_helper_0_0_1_finder.py
venv/Lib/site-packages/_virtualenv.py
venv/Lib/site-packages/docopt.py
venv/Lib/site-packages/github_release.py
venv/Lib/site-packages/link_header.py
venv/Lib/site-packages/publish.py
venv/Lib/site-packages/six.py
venv/Lib/site-packages/Xlib/X.py
venv/Lib/site-packages/Xlib/XK.py
venv/Lib/site-packages/Xlib/Xatom.py
venv/Lib/site-packages/Xlib/Xcursorfont.py
venv/Lib/site-packages/Xlib/Xutil.py
venv/Lib/site-packages/Xlib/__init__.py
venv/Lib/site-packages/Xlib/display.py
venv/Lib/site-packages/Xlib/error.py
venv/Lib/site-packages/Xlib/rdb.py
venv/Lib/site-packages/Xlib/threaded.py
venv/Lib/site-packages/Xlib/xauth.py
venv/Lib/site-packages/Xlib/ext/__init__.py
venv/Lib/site-packages/Xlib/ext/composite.py
venv/Lib/site-packages/Xlib/ext/randr.py
venv/Lib/site-packages/Xlib/ext/record.py
venv/Lib/site-packages/Xlib/ext/shape.py
venv/Lib/site-packages/Xlib/ext/xinerama.py
venv/Lib/site-packages/Xlib/ext/xtest.py
venv/Lib/site-packages/Xlib/keysymdef/__init__.py
venv/Lib/site-packages/Xlib/keysymdef/apl.py
venv/Lib/site-packages/Xlib/keysymdef/arabic.py
venv/Lib/site-packages/Xlib/keysymdef/cyrillic.py
venv/Lib/site-packages/Xlib/keysymdef/greek.py
venv/Lib/site-packages/Xlib/keysymdef/hebrew.py
venv/Lib/site-packages/Xlib/keysymdef/katakana.py
venv/Lib/site-packages/Xlib/keysymdef/korean.py
venv/Lib/site-packages/Xlib/keysymdef/latin1.py
venv/Lib/site-packages/Xlib/keysymdef/latin2.py
venv/Lib/site-packages/Xlib/keysymdef/latin3.py
venv/Lib/site-packages/Xlib/keysymdef/latin4.py
venv/Lib/site-packages/Xlib/keysymdef/miscellany.py
venv/Lib/site-packages/Xlib/keysymdef/publishing.py
venv/Lib/site-packages/Xlib/keysymdef/special.py
venv/Lib/site-packages/Xlib/keysymdef/technical.py
