Metadata-Version: 2.1
Name: game-bot-helper
Version: 0.0.1
Summary: A Helper, that accelerates the process of creating a bot for a game
Author-email: Hell Brands <hell_brands@outlook.com>
License: Copyright 2023 Hell Brands
Keywords: game,bot,helper
Classifier: Development Status :: 1 - Planning
Classifier: Environment :: Other Environment
Classifier: Intended Audience :: Developers
Classifier: License :: OSI Approved :: MIT License
Classifier: Natural Language :: English
Classifier: Operating System :: OS Independent
Classifier: Programming Language :: Python :: 3.12
Classifier: Topic :: Games/Entertainment
Classifier: Topic :: Software Development :: Libraries :: Python Modules
Classifier: Topic :: Utilities
Requires-Python: >=3.11
License-File: LICENSE.md
Requires-Dist: pyautogui
Requires-Dist: pynput
